willchan/__init__.py
willchan/__version__.py
willchan/core.py
willchan/utils/__init__.py
willchan/utils/cal_geodata.py
willchan/utils/cal_raster_in_shp.py
willchan/utils/data_convert.py
willchan/utils/deepl_translation.py
willchan/utils/mutil_task.py
willchan/utils/sqlite3_pool.py
willchan-0.1.9.1.dist-info/LICENSE
willchan-0.1.9.1.dist-info/METADATA
willchan-0.1.9.1.dist-info/WHEEL
willchan-0.1.9.1.dist-info/top_level.txt
willchan-0.1.9.1.dist-info/RECORD
